Metadata-Version: 2.1
Name: tyu-schematicpy
Version: 24.11.2
Summary: Package for biomedical data model and metadata ingress management
Home-page: https://github.com/Sage-Bionetworks/schematic
Keywords: schema,metadata,validation,data model,linked data
Author: Milen Nikolov
Author-email: milen.nikolov@sagebase.org
Requires-Python: >=3.9.0,<3.11
Classifier: Development Status :: 4 - Beta
Classifier: Environment :: Console
Classifier: Intended Audience :: Science/Research
Classifier: Programming Language :: Python :: 3
Classifier: Programming Language :: Python :: 3.9
Classifier: Programming Language :: Python :: 3.10
Classifier: Topic :: Software Development :: Libraries :: Python Modules
Provides-Extra: api
Provides-Extra: aws
Requires-Dist: Flask (==2.1.3)
Requires-Dist: Flask-Cors (>=3.0.10,<4.0.0)
Requires-Dist: Jinja2 (>2.11.3) ; extra == "api"
Requires-Dist: PyJWT (>=2.9.0,<3.0.0)
Requires-Dist: PyYAML (>=6.0.0,<7.0.0)
Requires-Dist: asyncio (>=3.4.3,<4.0.0)
Requires-Dist: backports.zoneinfo (>=0.2.1,<0.3.0) ; python_version < "3.9"
Requires-Dist: click (>=8.0.0,<9.0.0)
Requires-Dist: click-log (>=0.4.0,<0.5.0)
Requires-Dist: connexion[swagger-ui] (>=2.8.0,<3.0.0)
Requires-Dist: dataclasses-json (>=0.6.1,<0.7.0)
Requires-Dist: dateparser (>=1.1.4,<2.0.0)
Requires-Dist: google-api-python-client (>=2.0.0,<3.0.0)
Requires-Dist: google-auth-httplib2 (>=0.1.0,<0.2.0)
Requires-Dist: google-auth-oauthlib (>=0.8.0,<0.9.0)
Requires-Dist: graphviz (>=0.20.0,<0.21.0)
Requires-Dist: great-expectations (>=0.15.0,<0.16.0)
Requires-Dist: inflection (>=0.5.1,<0.6.0)
Requires-Dist: itsdangerous (>=2.0.0,<3.0.0)
Requires-Dist: jsonschema (>=4.0.0,<5.0.0)
Requires-Dist: networkx (>=2.2.8)
Requires-Dist: numpy (>=1.26.4,<2.0.0)
Requires-Dist: oauth2client (>=4.1.0,<5.0.0)
Requires-Dist: openpyxl (>=3.0.9,<4.0.0)
Requires-Dist: opentelemetry-api (>=1.21.0) ; extra == "api"
Requires-Dist: opentelemetry-exporter-otlp-proto-http (>=1.0.0,<2.0.0) ; extra == "api"
Requires-Dist: opentelemetry-instrumentation-flask (>=0.48b0)
Requires-Dist: opentelemetry-sdk (>=1.21.0) ; extra == "api"
Requires-Dist: pandarallel (>=1.6.4,<2.0.0)
Requires-Dist: pandas (>=2.2.2,<3.0.0)
Requires-Dist: pydantic (>=1.10.4,<2.0.0)
Requires-Dist: pygsheets (>=2.0.4,<3.0.0)
Requires-Dist: pyopenssl (>=23.0.0,<24.0.0) ; extra == "api"
Requires-Dist: rdflib (>=6.0.0,<7.0.0)
Requires-Dist: requests-oauth2client (>=1.6.0)
Requires-Dist: setuptools (>=66.0.0,<67.0.0)
Requires-Dist: synapseclient (==4.6.0)
Requires-Dist: tenacity (>=8.0.1,<9.0.0)
Requires-Dist: toml (>=0.10.2,<0.11.0)
Requires-Dist: uWSGI (>=2.0.21,<3.0.0) ; extra == "aws"
Project-URL: Documentation, https://github.com/Sage-Bionetworks/schematic
Project-URL: Repository, https://github.com/Sage-Bionetworks/schematic
